cxcli/__init__.py
cxcli/__main__.py
cxcli/clidriver.py
cxcli/syncspecs.py
cxcli-0.1.2.dist-info/LICENSE
cxcli-0.1.2.dist-info/METADATA
cxcli-0.1.2.dist-info/WHEEL
cxcli-0.1.2.dist-info/entry_points.txt
cxcli-0.1.2.dist-info/top_level.txt
cxcli-0.1.2.dist-info/RECORD
