Metadata-Version: 2.1
Name: cxcli
Version: 0.1.2
Summary: Experimental CLI for Citrix Cloud
Home-page: https://github.com/robertbreker/cxcli
Author: Robert Breker
Author-email: 
License: UNKNOWN
Platform: UNKNOWN
Classifier: Programming Language :: Python :: 3
Classifier: License :: OSI Approved :: BSD License
Classifier: Operating System :: OS Independent
Requires-Python: >=3.6
Requires-Dist: requests (>=2.25.0)
Requires-Dist: rich (>=9.8.2)
Requires-Dist: urllib3 (>=1.26.2)
Requires-Dist: argcomplete (>=1.12.2)
Requires-Dist: keyring (>=21.8.0)
Requires-Dist: PyYAML (>=5.4.1)
Requires-Dist: jmespath (>=0.10.0)
